iprPy/Settings.py
iprPy/VERSION
iprPy/__init__.py
iprPy/check_modules.py
iprPy/command_line.py
iprPy/fix_lammps_versions.py
iprPy/load_run_directory.py
iprPy/analysis/StackingFaultMEPCommander.py
iprPy/analysis/__init__.py
iprPy/analysis/add_urls_and_backup.py
iprPy/analysis/get_isolated_atom_energies.py
iprPy/analysis/match_reference_prototype.py
iprPy/analysis/process_relaxations.py
iprPy/analysis/stacking_fault_map_2D_mep.py
iprPy/analysis/PropertyProcessor/__init__.py
iprPy/analysis/PropertyProcessor/_crystal.py
iprPy/analysis/PropertyProcessor/_diatom.py
iprPy/analysis/PropertyProcessor/_elastic.py
iprPy/analysis/PropertyProcessor/_empty.py
iprPy/analysis/PropertyProcessor/_evsr.py
iprPy/analysis/PropertyProcessor/_mdliquid.py
iprPy/analysis/PropertyProcessor/_mdsolid.py
iprPy/analysis/PropertyProcessor/_mdthermo.py
iprPy/analysis/PropertyProcessor/_phonon.py
iprPy/analysis/PropertyProcessor/_point.py
iprPy/analysis/PropertyProcessor/_stacking.py
iprPy/analysis/PropertyProcessor/_surface.py
iprPy/analysis/md_solid_properties/__init__.py
iprPy/analysis/md_solid_properties/_md_solid_properties.py
iprPy/analysis/md_solid_properties/find_transition_temps.py
iprPy/analysis/md_solid_properties/load_transition_temp.py
iprPy/analysis/md_solid_properties/process_0K.py
iprPy/analysis/md_solid_properties/process_at_temp.py
iprPy/analysis/md_solid_properties/save_transition_temp.py
iprPy/analysis/md_solid_properties/update_untransformed_flag.py
iprPy/analysis/thermo/AnalyzeFE.py
iprPy/analysis/thermo/AnalyzeMD.py
iprPy/analysis/thermo/AnalyzeQHA.py
iprPy/analysis/thermo/Thermo.py
iprPy/analysis/thermo/ThermoSolid.py
iprPy/analysis/thermo/__init__.py
iprPy/calculation/Calculation.py
iprPy/calculation/__init__.py
iprPy/calculation/E_vs_r_scan/EvsRScan.py
iprPy/calculation/E_vs_r_scan/README.md
iprPy/calculation/E_vs_r_scan/__init__.py
iprPy/calculation/E_vs_r_scan/calculation_E_vs_r_scan.xsd
iprPy/calculation/E_vs_r_scan/calculation_E_vs_r_scan.xsl
iprpy-0.11.8.dist-info/licenses/LICENSE.TXT
iprpy-0.11.8.dist-info/METADATA
iprpy-0.11.8.dist-info/WHEEL
iprpy-0.11.8.dist-info/entry_points.txt
iprpy-0.11.8.dist-info/top_level.txt
iprpy-0.11.8.dist-info/RECORD
