Metadata-Version: 2.4
Name: iprPy
Version: 0.11.8
Summary: Interatomic Potential Repository Python Property Calculations and Tools
Home-page: https://github.com/usnistgov/iprPy
Author: Lucas Hale
Author-email: lucas.hale@nist.gov
Keywords: atom,atomic,atomistic,molecular dynamics,high-throughput,interatomic potential
Classifier: Development Status :: 4 - Beta
Classifier: Intended Audience :: Science/Research
Classifier: Natural Language :: English
Classifier: Programming Language :: Python :: 3.8
Classifier: Programming Language :: Python :: 3.9
Classifier: Programming Language :: Python :: 3.10
Classifier: Programming Language :: Python :: 3.11
Classifier: Topic :: Scientific/Engineering :: Physics
License-File: LICENSE.TXT
Requires-Dist: DataModelDict
Requires-Dist: numpy
Requires-Dist: matplotlib
Requires-Dist: scipy
Requires-Dist: pandas
Requires-Dist: atomman>=1.4.11
Requires-Dist: requests
Requires-Dist: bokeh
Requires-Dist: plotly
Dynamic: author
Dynamic: author-email
Dynamic: classifier
Dynamic: description
Dynamic: home-page
Dynamic: keywords
Dynamic: license-file
Dynamic: requires-dist
Dynamic: summary
